{
  "id": "B-039",
  "identifier": "com.usegdi.world-news",
  "version": "0.1.0",
  "url": "/boards/B-039",
  "boardInfo": {
    "name": "World News",
    "index": 39,
    "imageUrl": "/images/d1.jpg",
    "videoThumbUrl": "/images/B-039.mp4",
    "videoUrl": "",
    "boardType": "adhoc",
    "description": "Stay informed with the latest global events using the World News board. Access comprehensive coverage, breaking news, and in-depth analysis of international affairs. Explore diverse perspectives and deep insights to understand the world around you.",
    "descriptionLong": "The World News board is your gateway to global awareness. Whether it's political developments, economic trends, cultural movements, or environmental issues, this board brings together a wealth of information to keep you informed about the world. Dive into a comprehensive view of international affairs and stay up-to-date with all that unfolds.",
    "oneLiner": "Stay on top of global events with the World News board.",
    "oneLinerShort": "Stay on top of global events.",
    "header": "latest news from around the world",
    "logoColor": "#3366CC",
    "fields": [
      {
        "label": "region",
        "content": "Global"
      },
      {
        "label": "topic",
        "content": "World News"
      },
      {
        "label": "languages",
        "content": "English, Spanish, French, Chinese, Arabic"
      }
    ],
    "tags": [
      "news",
      "global",
      "updates",
      "information"
    ],
    "supportedResolutions": [
      "1920x1080",
      "1366x768",
      "1280x720"
    ],
    "tsVersion": "2024-02-07 10:30:00"
  },
  "author": "gdi",
  "dependencies": {
    "@gdi/store-base": "^1.0.0",
    "@gdi/ui": "^1.0.0",
    "@gdi/widgets-starter": "^1.0.0"
  },
  "apis": {},
  "defaults": {},
  "flowUrl": "/B-039/B-039.flow.json",
  "sourceUrl": "https://github.com/dht/gdi-assets/tree/reorg/boards/B-039",
  "npmUrl": "https://www.npmjs.com/package/@gdi/widgets-starter",
  "vscodeUrl": "https://vscode.dev/github/dht/gdi",
  "isActive": true,
  "isWip": true,
  "mobile": {
    "hidePrompt": true,
    "darkMode": true
  },
  "reviewInfo": {
    "reviewsCount": 0,
    "installationCount": 0,
    "rating": 0,
    "reviews": {}
  },
  "elements": {
    "default": {
      "e2": {
        "id": "e2",
        "widgetId": "com.usegdi.starter.earth",
        "title": "Earth",
        "position": {
          "x": 1,
          "y": 1
        },
        "dimension": {
          "x": 121,
          "y": 48
        },
        "boardId": "B-015",
        "flags": {},
        "props": {
          "sceneUrl": ""
        }
      },
      "e3": {
        "id": "e3",
        "widgetId": "com.usegdi.starter.logo",
        "title": "Logo",
        "position": {
          "x": 2,
          "y": 2
        },
        "dimension": {
          "x": 20,
          "y": 6
        },
        "props": {
          "darkMode": false
        },
        "boardId": "B-015",
        "flags": {}
      }
    },
    "mobile": {
      "e2": {
        "id": "e2",
        "widgetId": "com.usegdi.starter.earth",
        "title": "Earth",
        "position": {
          "x": 1,
          "y": 1
        },
        "dimension": {
          "x": 121,
          "y": 48
        },
        "boardId": "B-015",
        "flags": {},
        "props": {
          "sceneUrl": ""
        }
      }
    }
  }
}
